{
  "name": "Earl Saunders",
  "age": 52,
  "address": {
    "street": "Lesa Grove",
    "city": "Wamlofo",
    "state": "PA",
    "zip": "94793"
  },
  "contact": {
    "phone": "(303) 270-1378",
    "servicePhone": "800732131"
  },
  "birthday": "1989-03-22T08:29:37.359Z",
  "ip": "189.40.86.24",
  "foo": "bar",
  "profile": {
    "about": "Wut rew kilzuse zehgolpap zapuver geih jogarceg suapo vakevbim zuruta fo gozucec ka bid ali if wetcig. Ziti hiwad fi ta ifceni me cubge patcep lo ho ecehpu cenuhto tansema. Eveilowen fevak wujdozwo wom dik wulned gu cu dahibze uh rev ge kuvguin potec siziloub ijiju maejra attav. Fogzogik zusu ci zaje kok jic tuiwo puskorfi oneoji hu ur ibjablu lefovpej appa ifijip johi.",
    "bio": "Decan ecu ikulo zivne ike doimijav ozvaf zo pafardaw duobzi vukjognec ji emapagu touba ehni gog. Toke cewecife cu bawhaccad isnot jaite apu bog kul nol lavmaho nebkut ma joej corni awike. Ta jibepce obinolti duroh kibupbip gevavo saip jum nek fi iso rubekibit elpegsem zaisdi wih tas. Tag bo giupu ujigo huhu toan mic vo lifuwad tajoza rik maw vanin zum ravnegmuc zug. Bevwos ivuveso vawri jugod bak ponmecet rebwaliz eroave met uvkira te hil bi difsiv pisbikev."
  },
  "apiKey": "e966fce09d1ad0c439872827abdf33732cb5de9bbd8eb7112a01c8d5e6edb13c",
  "currency": {
    "code": "AED",
    "name": "United Arab Emirates Dirham"
  }
}